tensorhelper/__init__.py
tensorhelper/custom_tensor.py
tensorhelper-0.2.0.dist-info/LICENSE.txt
tensorhelper-0.2.0.dist-info/METADATA
tensorhelper-0.2.0.dist-info/WHEEL
tensorhelper-0.2.0.dist-info/top_level.txt
tensorhelper-0.2.0.dist-info/RECORD
