Metadata-Version: 2.1
Name: tensorhelper
Version: 0.2.0
Summary: A helper function for data analytics and machine learning
Home-page: https://github.com/Ifeanyi-omeck/tensorhelper
Author: ifeanyi_omeck
Author-email: kifeanyi@gmail.com
License: UNKNOWN
Keywords: python,confusion_matrix,loss_curves,accuracy_curves,random_images
Platform: UNKNOWN
Classifier: Development Status :: 1 - Planning
Classifier: Intended Audience :: Developers
Classifier: Programming Language :: Python :: 3
Classifier: Operating System :: Unix
Classifier: Operating System :: MacOS :: MacOS X
Classifier: Operating System :: Microsoft :: Windows
License-File: LICENSE.txt
